fleece_network-0.4.3.dist-info/METADATA
fleece_network-0.4.3.dist-info/WHEEL
fleece_network/peer.py
fleece_network/__init__.py
fleece_network/py.typed
fleece_network/serde.py
fleece_network/fleece_network_rust.cpython-311-x86_64-linux-gnu.so
fleece_network-0.4.3.dist-info/RECORD
